dbsqlclone/__init__.py
dbsqlclone/clone_resources.py
dbsqlclone/utils/__init__.py
dbsqlclone/utils/client.py
dbsqlclone/utils/clone_dashboard.py
dbsqlclone/utils/dump_dashboard.py
dbsqlclone/utils/load_dashboard.py
dbsqlclone-0.1.24.dist-info/LICENCE
dbsqlclone-0.1.24.dist-info/METADATA
dbsqlclone-0.1.24.dist-info/WHEEL
dbsqlclone-0.1.24.dist-info/top_level.txt
dbsqlclone-0.1.24.dist-info/RECORD
