Metadata-Version: 2.1
Name: dbsqlclone
Version: 0.1.24
Summary: UNKNOWN
License: UNKNOWN
Platform: UNKNOWN
Requires-Dist: requests
